certbot_dns_loopia.py
certbot_dns_loopia-1.0.1.dist-info/LICENSE
certbot_dns_loopia-1.0.1.dist-info/METADATA
certbot_dns_loopia-1.0.1.dist-info/WHEEL
certbot_dns_loopia-1.0.1.dist-info/entry_points.txt
certbot_dns_loopia-1.0.1.dist-info/top_level.txt
certbot_dns_loopia-1.0.1.dist-info/RECORD
