Metadata-Version: 2.1
Name: certbot-dns-loopia
Version: 1.0.1
Summary: Loopia DNS authentication plugin for Certbot
Home-page: https://www.github.com/runfalk/certbot-loopia
Author: Andreas Runfalk
Author-email: andreas@runfalk.se
License: BSD
Classifier: Development Status :: 2 - Pre-Alpha
Classifier: Environment :: Plugins
Classifier: Intended Audience :: Developers
Classifier: License :: OSI Approved :: BSD License
Classifier: Programming Language :: Python
Classifier: Programming Language :: Python :: 3.6
Classifier: Programming Language :: Python :: 3.7
Classifier: Programming Language :: Python :: 3.8
Classifier: Programming Language :: Python :: 3.9
Classifier: Topic :: Internet :: Name Service (DNS)
Classifier: Topic :: System :: Systems Administration
Classifier: Topic :: Utilities
License-File: LICENSE
Requires-Dist: acme (>=1.8.0)
Requires-Dist: certbot (>=1.7.0)
Requires-Dist: loopialib (>=0.2.0)
Provides-Extra: dev
Requires-Dist: pytest ; extra == 'dev'
Requires-Dist: wheel ; extra == 'dev'
Requires-Dist: pylint (==2.13.9) ; extra == 'dev'
